LICENSE
README.md
setup.py
convert/__init__.py
convert/utils.py
dataset_convertor.egg-info/PKG-INFO
dataset_convertor.egg-info/SOURCES.txt
dataset_convertor.egg-info/dependency_links.txt
dataset_convertor.egg-info/top_level.txt