Metadata-Version: 2.1
Name: dataset-convertor
Version: 0.0.2
Summary: Convert Dataset from one format to another format
Home-page: https://github.com/codePerfectPlus/dataset-convertor
Author: CodePerfectPlus
Author-email: deepak008@live.com
Classifier: Programming Language :: Python :: 3
Classifier: License :: OSI Approved :: MIT License
Classifier: Operating System :: OS Independent
License-File: LICENSE
